tracktour/__init__.py
tracktour/_costs.py
tracktour/_graph_util.py
tracktour/_io_util.py
tracktour/_oracle.py
tracktour/_tracker.py
tracktour/_viz_util.py
tracktour/cli.py
tracktour/napari.yaml
tracktour/scales.yaml
tracktour/_napari/__init__.py
tracktour/_napari/_graph_conversion_util.py
tracktour/_napari/_merge_explorer.py
tracktour/_napari/_solver.py
tracktour/_napari/_track_editor.py
tracktour-0.0.6.dist-info/METADATA
tracktour-0.0.6.dist-info/WHEEL
tracktour-0.0.6.dist-info/entry_points.txt
tracktour-0.0.6.dist-info/licenses/LICENSE
tracktour-0.0.6.dist-info/RECORD
