Metadata-Version: 2.3
Name: tracktour
Version: 0.0.6
Summary: Network flow based tracker with guided error correction
Project-URL: homepage, https://github.com/DragaDoncila/tracktour
Project-URL: repository, https://github.com/DragaDoncila/tracktour
Author-email: Draga Doncila Pop <ddoncila@gmail.com>
License: BSD 3-Clause License
License-File: LICENSE
Classifier: Intended Audience :: Science/Research
Classifier: License :: OSI Approved :: BSD License
Classifier: Operating System :: OS Independent
Classifier: Programming Language :: Python :: 3
Classifier: Programming Language :: Python :: 3.8
Classifier: Programming Language :: Python :: 3.9
Classifier: Programming Language :: Python :: 3.10
Classifier: Topic :: Scientific/Engineering
Classifier: Topic :: Scientific/Engineering :: Bio-Informatics
Classifier: Topic :: Scientific/Engineering :: Image Processing
Classifier: Topic :: Scientific/Engineering :: Information Analysis
Classifier: Topic :: Scientific/Engineering :: Visualization
Requires-Python: >=3.8
Requires-Dist: gurobipy
Requires-Dist: imagecodecs
Requires-Dist: networkx
Requires-Dist: numpy
Requires-Dist: pandas
Requires-Dist: pydantic
Requires-Dist: pyyaml
Requires-Dist: scikit-image
Requires-Dist: scipy
Requires-Dist: tifffile
Requires-Dist: tqdm
Requires-Dist: typer
Provides-Extra: dev
Requires-Dist: pre-commit; extra == 'dev'
Provides-Extra: napari
Requires-Dist: arboretum; extra == 'napari'
Requires-Dist: napari; extra == 'napari'
Requires-Dist: napari-graph; extra == 'napari'
Provides-Extra: test
Requires-Dist: pytest>=6.0; extra == 'test'
